{
  "TInstance":
  [
    {
      "mesh": "data/meshes/column_in_04.instanced_mesh",
      "data":
      [
        {
          "pos": "-308.365 38.341 -289.483",
          "scale": 1.0,
          "rot": "0.0 0.0 0.0 -1.0"
        },
        {
          "pos": "-271.469 38.341 -306.394",
          "scale": 1.0,
          "rot": "0.0 0.0 0.0 -1.0"
        },
        {
          "pos": "-243.493 38.341 -323.073",
          "scale": 1.0,
          "rot": "0.0 0.0 0.0 -1.0"
        },
        {
          "pos": "-210.679 38.341 -339.678",
          "scale": 1.0,
          "rot": "0.0 0.0 0.0 -1.0"
        },
        {
          "pos": "-182.853 38.341 -270.358",
          "scale": 1.0,
          "rot": "0.0 0.0 0.0 -1.0"
        },
        {
          "pos": "-208.981 38.341 -255.763",
          "scale": 1.0,
          "rot": "0.0 0.0 0.0 -1.0"
        },
        {
          "pos": "-245.07 38.341 -239.803",
          "scale": 1.0,
          "rot": "0.0 0.0 0.0 -1.0"
        },
        {
          "pos": "-279.637 38.341 -228.613",
          "scale": 1.0,
          "rot": "0.0 0.0 0.0 -1.0"
        },
        {
          "pos": "-181.428 38.341 -364.498",
          "scale": 1.0,
          "rot": "0.0 0.0 0.0 -1.0"
        },
        {
          "pos": "-143.63 38.341 -293.773",
          "scale": 1.0,
          "rot": "0.0 0.0 0.0 -1.0"
        },
        {
          "pos": "-173.196 32.8596 -219.716",
          "scale": 1.0,
          "rot": "0.0 0.0 0.0 -1.0"
        },
        {
          "pos": "-154.597 32.8596 -228.58",
          "scale": 1.0,
          "rot": "0.0 0.0 0.0 -1.0"
        },
        {
          "pos": "-34.3032 24.0529 -212.868",
          "scale": 1.0,
          "rot": "0.0 0.0 0.0 -1.0"
        },
        {
          "pos": "-33.9383 23.9909 -170.427",
          "scale": 1.0,
          "rot": "0.0 0.0 0.0 -1.0"
        },
        {
          "pos": "42.5848 24.8088 -170.983",
          "scale": 1.0,
          "rot": "0.0 0.0 0.0 -1.0"
        },
        {
          "pos": "38.8937 24.7258 -215.835",
          "scale": 1.0,
          "rot": "0.0 0.0 0.0 -1.0"
        },
        {
          "pos": "139.857 49.0005 -235.867",
          "scale": 1.0,
          "rot": "0.0 0.0 0.0 -1.0"
        },
        {
          "pos": "-233.858 39.0772 -176.162",
          "scale": 1.0,
          "rot": "0.690346 0.139125 0.165802 -0.690346"
        },
        {
          "pos": "-222.842 39.0772 -154.468",
          "scale": 1.0,
          "rot": "0.608537 0.340276 0.365719 -0.616559"
        },
        {
          "pos": "122.303 17.9141 -184.684",
          "scale": 1.0,
          "rot": "0.651066 0.256888 0.283161 -0.655699"
        }
      ]
    }
  ]
}