<?xml version="1.0" encoding="UTF-8"?>
<objects serializationModel="Studio.01.10.00">
    <object class="AudioFile" id="{9c6afafe-270c-4561-a102-d65e7708a93a}">
        <property name="assetPath">
            <value>salto_corto_vuelo_05.wav</value>
        </property>
        <property name="frequencyInKHz">
            <value>44.0999985</value>
        </property>
        <property name="channelCount">
            <value>2</value>
        </property>
        <property name="length">
            <value>2.5766893424036281</value>
        </property>
        <relationship name="masterAssetFolder">
            <destination>{0bb3bd78-43c6-403a-a6e2-7cb3cb37be71}</destination>
        </relationship>
    </object>
</objects>
